hgutils.py
hgutils-0.0.3.dist-info/LICENSE
hgutils-0.0.3.dist-info/METADATA
hgutils-0.0.3.dist-info/WHEEL
hgutils-0.0.3.dist-info/top_level.txt
hgutils-0.0.3.dist-info/RECORD
