Metadata-Version: 2.1
Name: hgutils
Version: 0.0.3
Summary: Utilities package while developing and implementing python tools
Author: Hitesh Gulati
Classifier: Programming Language :: Python :: 3
Classifier: License :: OSI Approved :: MIT License
Classifier: Operating System :: OS Independent
Requires-Python: >=3.6
License-File: LICENSE
